integration_tests/__init__.py
integration_tests/abnormal_state.json
integration_tests/acceptance.py
integration_tests/configured_catalog.json
integration_tests/invalid_config.json
integration_tests/sample_config.json
integration_tests/sample_state.json
source_dz_zoho_books/__init__.py
source_dz_zoho_books/api.py
source_dz_zoho_books/auth.py
source_dz_zoho_books/source.py
source_dz_zoho_books/spec.yaml
source_dz_zoho_books/schemas/bankaccounts.json
source_dz_zoho_books/schemas/banktransactions.json
source_dz_zoho_books/schemas/basecurrencyadjustment.json
source_dz_zoho_books/schemas/bills.json
source_dz_zoho_books/schemas/chartofaccounts.json
source_dz_zoho_books/schemas/contacts.json
source_dz_zoho_books/schemas/creditnotes.json
source_dz_zoho_books/schemas/currencies.json
source_dz_zoho_books/schemas/customerpayments.json
source_dz_zoho_books/schemas/estimates.json
source_dz_zoho_books/schemas/expenses.json
source_dz_zoho_books/schemas/invoices.json
source_dz_zoho_books/schemas/items.json
source_dz_zoho_books/schemas/journals.json
source_dz_zoho_books/schemas/projects.json
source_dz_zoho_books/schemas/purchaseorders.json
source_dz_zoho_books/schemas/recurring_bills.json
source_dz_zoho_books/schemas/recurring_expenses.json
source_dz_zoho_books/schemas/recurring_invoices.json
source_dz_zoho_books/schemas/retainerinvoices.json
source_dz_zoho_books/schemas/salesorders.json
source_dz_zoho_books/schemas/time_entries.json
source_dz_zoho_books/schemas/users.json
source_dz_zoho_books/schemas/vendor_credits.json
source_dz_zoho_books/schemas/vendorpayments.json
unit_tests/__init__.py
unit_tests/test_incremental_streams.py
unit_tests/test_source.py
unit_tests/test_streams.py
source_dz_zoho_books-0.0.0.dist-info/METADATA
source_dz_zoho_books-0.0.0.dist-info/WHEEL
source_dz_zoho_books-0.0.0.dist-info/top_level.txt
source_dz_zoho_books-0.0.0.dist-info/RECORD
